{
  "manifestVersion": "3.2",
  "admin": {
    "address": "0x9fb86a021B57692C38D48d1B9c68399F7829A3E2",
    "txHash": "0x373702a3d06bd76df570d39de72b92a447f95703375bbec8451f0763fbf025b9"
  },
  "proxies": [
    {
      "address": "0xcFd5A247f6aC32AE03C2b0C343327B32174e7eFF",
      "txHash": "0xd73a64cad0e21b07d3a2a5ca5136731b1a3a48233788a638dbea19d2f361d8de",
      "kind": "transparent"
    },
    {
      "address": "0x5aA319f0150A04C8824dF63176361d1Be5D2073e",
      "txHash": "0x4bfd2d0914171c24f07405392059be0379ed6f0d1c99c5fbce124c31fa6f383a",
      "kind": "transparent"
    }
  ],
  "impls": {
    "041666f7011c9b5a8bf6080dc0792fc660df15767181dcdce8b38677929c9b6e": {
      "address": "0x04AcbC6f9721DB6DB516B8b222BC547c46Cea4E3",
      "txHash": "0x7bdebb3adc7d11c1617d2a1cbcb1212052497e66426e04fbdb082b931af0f0c9",
      "layout": {
        "solcVersion": "0.8.17",
        "storage": [
          {
            "label": "_initialized",
            "offset": 0,
            "slot": "0",
            "type": "t_uint8",
            "contract": "Initializable",
            "src": "@openzeppelin/contracts-upgradeable/proxy/utils/Initializable.sol:63",
            "retypedFrom": "bool"
          },
          {
            "label": "_initializing",
            "offset": 1,
            "slot": "0",
            "type": "t_bool",
            "contract": "Initializable",
            "src": "@openzeppelin/contracts-upgradeable/proxy/utils/Initializable.sol:68"
          },
          {
            "label": "numSodas",
            "offset": 0,
            "slot": "1",
            "type": "t_uint256",
            "contract": "VendingMachineV1",
            "src": "contracts/VendingMachineV1.sol:9"
          },
          {
            "label": "owner",
            "offset": 0,
            "slot": "2",
            "type": "t_address",
            "contract": "VendingMachineV1",
            "src": "contracts/VendingMachineV1.sol:10"
          }
        ],
        "types": {
          "t_address": {
            "label": "address",
            "numberOfBytes": "20"
          },
          "t_bool": {
            "label": "bool",
            "numberOfBytes": "1"
          },
          "t_uint256": {
            "label": "uint256",
            "numberOfBytes": "32"
          },
          "t_uint8": {
            "label": "uint8",
            "numberOfBytes": "1"
          }
        },
        "namespaces": {}
      }
    },
    "14bc4f5724a693c7b8a95e05fea94776bfdbeacb0942fef6221d542713dbc3f4": {
      "address": "0x86A2d9Ae6842ebcfe9d5e1A720EB60C288e1e715",
      "txHash": "0xf36dc3462ca307e8558c37ac455770da0d6d3d6a97902bf9be3aa937f14356f3",
      "layout": {
        "solcVersion": "0.8.17",
        "storage": [
          {
            "label": "_initialized",
            "offset": 0,
            "slot": "0",
            "type": "t_uint8",
            "contract": "Initializable",
            "src": "@openzeppelin/contracts-upgradeable/proxy/utils/Initializable.sol:63",
            "retypedFrom": "bool"
          },
          {
            "label": "_initializing",
            "offset": 1,
            "slot": "0",
            "type": "t_bool",
            "contract": "Initializable",
            "src": "@openzeppelin/contracts-upgradeable/proxy/utils/Initializable.sol:68"
          },
          {
            "label": "numSodas",
            "offset": 0,
            "slot": "1",
            "type": "t_uint256",
            "contract": "VendingMachineV2",
            "src": "contracts/VendingMachineV2.sol:9"
          },
          {
            "label": "owner",
            "offset": 0,
            "slot": "2",
            "type": "t_address",
            "contract": "VendingMachineV2",
            "src": "contracts/VendingMachineV2.sol:10"
          },
          {
            "label": "sodaPurchases",
            "offset": 0,
            "slot": "3",
            "type": "t_mapping(t_address,t_uint256)",
            "contract": "VendingMachineV2",
            "src": "contracts/VendingMachineV2.sol:12"
          }
        ],
        "types": {
          "t_address": {
            "label": "address",
            "numberOfBytes": "20"
          },
          "t_bool": {
            "label": "bool",
            "numberOfBytes": "1"
          },
          "t_mapping(t_address,t_uint256)": {
            "label": "mapping(address => uint256)",
            "numberOfBytes": "32"
          },
          "t_uint256": {
            "label": "uint256",
            "numberOfBytes": "32"
          },
          "t_uint8": {
            "label": "uint8",
            "numberOfBytes": "1"
          }
        },
        "namespaces": {}
      }
    },
    "d30c51944a5b78ab36abe843e0d49157583eda6ea468c0c743aee0ef2f0c77a3": {
      "address": "0x7B235Cfcb0E3262F3a99a8391A06f1674C11Dd5b",
      "txHash": "0x95c9a160d83ef846ca278ef2354ed812276612941fab2cbe637e444262297b5e",
      "layout": {
        "solcVersion": "0.8.17",
        "storage": [
          {
            "label": "_initialized",
            "offset": 0,
            "slot": "0",
            "type": "t_uint8",
            "contract": "Initializable",
            "src": "@openzeppelin/contracts-upgradeable/proxy/utils/Initializable.sol:63",
            "retypedFrom": "bool"
          },
          {
            "label": "_initializing",
            "offset": 1,
            "slot": "0",
            "type": "t_bool",
            "contract": "Initializable",
            "src": "@openzeppelin/contracts-upgradeable/proxy/utils/Initializable.sol:68"
          },
          {
            "label": "numSodas",
            "offset": 0,
            "slot": "1",
            "type": "t_uint256",
            "contract": "VendingMachineV3",
            "src": "contracts/VendingMachineV3.sol:9"
          },
          {
            "label": "owner",
            "offset": 0,
            "slot": "2",
            "type": "t_address",
            "contract": "VendingMachineV3",
            "src": "contracts/VendingMachineV3.sol:10"
          },
          {
            "label": "sodaPurchases",
            "offset": 0,
            "slot": "3",
            "type": "t_mapping(t_address,t_uint256)",
            "contract": "VendingMachineV3",
            "src": "contracts/VendingMachineV3.sol:12"
          }
        ],
        "types": {
          "t_address": {
            "label": "address",
            "numberOfBytes": "20"
          },
          "t_bool": {
            "label": "bool",
            "numberOfBytes": "1"
          },
          "t_mapping(t_address,t_uint256)": {
            "label": "mapping(address => uint256)",
            "numberOfBytes": "32"
          },
          "t_uint256": {
            "label": "uint256",
            "numberOfBytes": "32"
          },
          "t_uint8": {
            "label": "uint8",
            "numberOfBytes": "1"
          }
        },
        "namespaces": {}
      }
    }
  }
}
